rdr/__init__.py
rdr/rdr.py
rdr/server.py
reader_toolbox-0.9.dist-info/LICENSE
reader_toolbox-0.9.dist-info/METADATA
reader_toolbox-0.9.dist-info/WHEEL
reader_toolbox-0.9.dist-info/entry_points.txt
reader_toolbox-0.9.dist-info/top_level.txt
reader_toolbox-0.9.dist-info/RECORD
