Metadata-Version: 2.1
Name: reader-toolbox
Version: 0.9
Summary: A command-line interface for creating and interacting with Distant Reader data sets (a.k.a. study carrels)
Home-page: https://github.com/ericleasemorgan/reader-toolbox
Author: Eric Lease Morgan
Author-email: emorgan@nd.edu
Project-URL: Bug Tracker, https://github.com/ericleasemorgan/reader-toolbox/issues
Classifier: Programming Language :: Python :: 3.9
Classifier: License :: OSI Approved :: GNU General Public License v2 (GPLv2)
Classifier: Operating System :: OS Independent
License-File: LICENSE
Requires-Dist: catalogue >=1.0.0
Requires-Dist: click >=7.1.2
Requires-Dist: datasette >=0.55
Requires-Dist: matplotlib >=3.4.2
Requires-Dist: nltk >=3.6.2
Requires-Dist: tika >=1.24
Requires-Dist: pandas <=1.5.2
Requires-Dist: requests >=2.26.0
Requires-Dist: pytextrank >=3.2.2
Requires-Dist: scikit-learn >=0.23.2
Requires-Dist: scipy >=1.7.1
Requires-Dist: srsly >=1.0.5
Requires-Dist: textacy >=0.12.0
Requires-Dist: pytextrank
Requires-Dist: wordcloud
Requires-Dist: networkx <=2.8.7
Requires-Dist: gensim
Requires-Dist: rdflib
